README
setup.py
dummy/__init__.py
dummy/idostuff.py
seed_test.egg-info/PKG-INFO
seed_test.egg-info/SOURCES.txt
seed_test.egg-info/dependency_links.txt
seed_test.egg-info/top_level.txt