Metadata-Version: 1.0
Name: seed-test
Version: 0.0.4
Summary: two
